README
setup.cfg
setup.py
myself/__init__.py
myself.egg-info/PKG-INFO
myself.egg-info/SOURCES.txt
myself.egg-info/dependency_links.txt
myself.egg-info/entry_points.txt
myself.egg-info/not-zip-safe
myself.egg-info/top_level.txt