Metadata-Version: 1.0
Name: myself
Version: 0.0001
Summary: Find where myself is
Home-page: UNKNOWN
Author: Xupeng Yun
Author-email: xupeng@xupeng.me
License: MIT
Platform: UNKNOWN
